{
  "kind": "singleType",
  "collectionName": "customs",
  "info": {
    "singularName": "custom",
    "pluralName": "customs",
    "displayName": "Custom",
    "description": ""
  },
  "options": {
    "draftAndPublish": true
  },
  "pluginOptions": {
    "i18n": {
      "localized": true
    }
  },
  "attributes": {
    "content": {
      "type": "component",
      "repeatable": false,
      "pluginOptions": {
        "i18n": {
          "localized": true
        }
      },
      "component": "custom.images-url-row",
      "required": true
    }
  }
}
